controku/__init__.py
controku/controku.py
controku/main.py
controku/images/controku.png
controku/images/hicolor/scalable/actions/media-down-symbolic.svg
controku/images/hicolor/scalable/actions/media-left-symbolic.svg
controku/images/hicolor/scalable/actions/media-play-pause-symbolic.svg
controku/images/hicolor/scalable/actions/media-right-symbolic.svg
controku/images/hicolor/scalable/actions/media-up-symbolic.svg
controku/images/hicolor/scalable/actions/refresh-symbolic.svg
controku-1.1.0.dist-info/LICENSE
controku-1.1.0.dist-info/METADATA
controku-1.1.0.dist-info/WHEEL
controku-1.1.0.dist-info/entry_points.txt
controku-1.1.0.dist-info/top_level.txt
controku-1.1.0.dist-info/RECORD
