Metadata-Version: 2.1
Name: controku
Version: 1.1.0
Summary: Control Roku devices from the comfort of your own desktop
Author-email: Ben Westover <me@benthetechguy.net>
Project-URL: Homepage, https://github.com/benthetechguy/controku
Project-URL: Bug Tracker, https://github.com/benthetechguy/controku/issues
Keywords: roku,remote
Classifier: Programming Language :: Python :: 3.10
Classifier: License :: OSI Approved :: GNU General Public License v3 (GPLv3)
Classifier: Environment :: X11 Applications :: GTK
Classifier: Intended Audience :: Developers
Classifier: Intended Audience :: End Users/Desktop
Classifier: Operating System :: OS Independent
Classifier: Topic :: Communications
Classifier: Topic :: Home Automation
Classifier: Topic :: Software Development :: Libraries :: Python Modules
Classifier: Topic :: Software Development :: User Interfaces
Requires-Python: >=3.10
License-File: LICENSE
Requires-Dist: requests
Requires-Dist: ssdpy
Provides-Extra: gui
Requires-Dist: PyGObject ; extra == 'gui'
Requires-Dist: appdirs ; extra == 'gui'
